season_polar_plots/__init__.py
season_polar_plots/season.py
season_polar_plots-0.0.6.dist-info/LICENSE
season_polar_plots-0.0.6.dist-info/METADATA
season_polar_plots-0.0.6.dist-info/WHEEL
season_polar_plots-0.0.6.dist-info/top_level.txt
season_polar_plots-0.0.6.dist-info/RECORD
