Metadata-Version: 2.1
Name: season-polar-plots
Version: 0.0.6
Summary: Create polar plots to display seasonal trends in time series data.
Author-email: Marleen Schübl <marleen@schuebl.de>
License: MIT
Project-URL: Homepage, https://github.com/msiambro/season_polar_plots/
Classifier: Programming Language :: Python :: 3
Classifier: License :: OSI Approved :: MIT License
Classifier: Operating System :: OS Independent
Requires-Python: >=3.7
License-File: LICENSE
Requires-Dist: matplotlib
Requires-Dist: numpy
Requires-Dist: pandas
Requires-Dist: seaborn
Requires-Dist: scipy
